rh_email_tpl/__init__.py
rh_email_tpl/apps.py
rh_email_tpl/email_message.py
rh_email_tpl/static/img/email/som/cta.png
rh_email_tpl/static/img/email/som/eyecatcher_impressions.png
rh_email_tpl/static/img/email/som/icon-date_range.png
rh_email_tpl/static/img/email/som/icon-find_in_page.png
rh_email_tpl/static/img/email/som/icon-info.png
rh_email_tpl/static/img/email/som/icon-laptop.png
rh_email_tpl/static/img/email/som/icon-record_voice_over.png
rh_email_tpl/static/img/email/som/icon-visibility.png
rh_email_tpl/static/img/email/som/logo_regiohelden.png
rh_email_tpl/static/img/email/som/logo_regiohelden_omnea.png
rh_email_tpl/static/img/email/som/logo_som.png
rh_email_tpl/static/img/email/som/logo_stroeer_regiohelden_omnea.png
rh_email_tpl/static/img/email/som/product_display.png
rh_email_tpl/static/img/email/som/product_facebook.png
rh_email_tpl/static/img/email/som/product_googleads.png
rh_email_tpl/static/img/email/som/product_inapp.png
rh_email_tpl/static/img/email/som/product_listings.png
rh_email_tpl/static/img/email/som/product_seo.png
rh_email_tpl/static/img/email/som/product_website.png
rh_email_tpl/static/img/email/som/warning.png
rh_email_tpl/templates/email/base.txt
rh_email_tpl/templates/email/footer.txt
rh_email_tpl/templates/email/som/base.html
rh_email_tpl/templates/email/som/base.txt
rh_email_tpl/templates/email/som/email_template_components.html
rh_email_tpl/templates/email/som/empty.html
rh_email_tpl/templates/email/som/tags/bold.html
rh_email_tpl/templates/email/som/tags/bold.txt
rh_email_tpl/templates/email/som/tags/button.html
rh_email_tpl/templates/email/som/tags/button.txt
rh_email_tpl/templates/email/som/tags/center.html
rh_email_tpl/templates/email/som/tags/center.txt
rh_email_tpl/templates/email/som/tags/code.html
rh_email_tpl/templates/email/som/tags/code.txt
rh_email_tpl/templates/email/som/tags/color.html
rh_email_tpl/templates/email/som/tags/color.txt
rh_email_tpl/templates/email/som/tags/color_preview.html
rh_email_tpl-0.4.0.dist-info/licenses/LICENSE
rh_email_tpl-0.4.0.dist-info/METADATA
rh_email_tpl-0.4.0.dist-info/WHEEL
rh_email_tpl-0.4.0.dist-info/top_level.txt
rh_email_tpl-0.4.0.dist-info/RECORD
